dsw/database/__init__.py
dsw/database/build_info.py
dsw/database/database.py
dsw/database/model.py
dsw_database-4.26.1.dist-info/licenses/LICENSE
dsw_database-4.26.1.dist-info/METADATA
dsw_database-4.26.1.dist-info/WHEEL
dsw_database-4.26.1.dist-info/top_level.txt
dsw_database-4.26.1.dist-info/RECORD
