Metadata-Version: 2.4
Name: dsw-database
Version: 4.26.1
Summary: Library for managing DSW database
Author-email: Marek Suchánek <marek.suchanek@ds-wizard.org>
License: Apache License 2.0
Project-URL: Homepage, https://ds-wizard.org
Project-URL: Repository, https://github.com/ds-wizard/engine-tools
Project-URL: Documentation, https://guide.ds-wizard.org
Keywords: dsw,database
Classifier: Development Status :: 5 - Production/Stable
Classifier: License :: OSI Approved :: Apache Software License
Classifier: Programming Language :: Python
Classifier: Programming Language :: Python :: 3.12
Classifier: Programming Language :: Python :: 3.13
Classifier: Topic :: Database
Classifier: Topic :: Utilities
Requires-Python: <4,>=3.12
License-File: LICENSE
Requires-Dist: psycopg[binary]
Requires-Dist: tenacity
Requires-Dist: dsw-config==4.26.1
Dynamic: license-file
